setup.py
requestQ/__init__.py
requestQ/setup.py
requestQ.egg-info/PKG-INFO
requestQ.egg-info/SOURCES.txt
requestQ.egg-info/dependency_links.txt
requestQ.egg-info/requires.txt
requestQ.egg-info/top_level.txt
requestQ/config/__init__.py
requestQ/config/sys_config.py
requestQ/package/__init__.py
requestQ/package/baseClass.py
requestQ/package/case.py
requestQ/package/domssql.py
requestQ/package/domysql.py
requestQ/package/domysql_yun.py
requestQ/package/dorequest.py
requestQ/package/edit.py
requestQ/package/item.py
requestQ/package/logger.py
requestQ/package/report.py
requestQ/test/__init__.py
requestQ/test/test_case.py
requestQ/test/test_item.py
requestQ/test/test_item2.py
requestQ/test/test_mureq.py
requestQ/test/test_print_log.py
requestQ/test/test_raw.py
requestQ/test/test_sss.py