Metadata-Version: 1.0
Name: requestQ
Version: 0.0.6
Summary: 封装了requests去接口测试
Home-page: https://gitee.com/tuboyou/requestQ
Author: lxch
Author-email: lixuechengde@163.com
License: MIT Licence
Keywords: pip,request,requests,requestQ
Platform: any
